odoo/addons/ssi_hr_cash_advance/README.rst
odoo/addons/ssi_hr_cash_advance/__init__.py
odoo/addons/ssi_hr_cash_advance/__manifest__.py
odoo/addons/ssi_hr_cash_advance/data/account_journal_data.xml
odoo/addons/ssi_hr_cash_advance/data/approval_template_data.xml
odoo/addons/ssi_hr_cash_advance/data/base_automation_data.xml
odoo/addons/ssi_hr_cash_advance/data/ir_actions_server_data.xml
odoo/addons/ssi_hr_cash_advance/data/ir_sequence_data.xml
odoo/addons/ssi_hr_cash_advance/data/policy_template_data.xml
odoo/addons/ssi_hr_cash_advance/data/sequence_template_data.xml
odoo/addons/ssi_hr_cash_advance/demo/account_account_demo.xml
odoo/addons/ssi_hr_cash_advance/demo/account_journal_demo.xml
odoo/addons/ssi_hr_cash_advance/demo/hr_expense_type_demo.xml
odoo/addons/ssi_hr_cash_advance/i18n/ssi_hr_cash_advance.pot
odoo/addons/ssi_hr_cash_advance/models/__init__.py
odoo/addons/ssi_hr_cash_advance/models/hr_cash_advance.py
odoo/addons/ssi_hr_cash_advance/models/hr_cash_advance_line.py
odoo/addons/ssi_hr_cash_advance/models/hr_cash_advance_settlement.py
odoo/addons/ssi_hr_cash_advance/models/hr_cash_advance_settlement_line.py
odoo/addons/ssi_hr_cash_advance/models/hr_expense_type.py
odoo/addons/ssi_hr_cash_advance/models/res_config_settings.py
odoo/addons/ssi_hr_cash_advance/security/ir.model.access.csv
odoo/addons/ssi_hr_cash_advance/security/ir_module_category_data.xml
odoo/addons/ssi_hr_cash_advance/security/ir_rule_data.xml
odoo/addons/ssi_hr_cash_advance/security/res_group_data.xml
odoo/addons/ssi_hr_cash_advance/static/description/icon.png
odoo/addons/ssi_hr_cash_advance/static/description/icon_timesheet.png
odoo/addons/ssi_hr_cash_advance/views/hr_cash_advance_views.xml
odoo/addons/ssi_hr_cash_advance/views/hr_cash_advance_views_settlement.xml
odoo/addons/ssi_hr_cash_advance/views/hr_expense_type_views.xml
odoo/addons/ssi_hr_cash_advance/views/res_config_settings_views.xml
odoo14_addon_ssi_hr_cash_advance-14.0.1.15.0.dist-info/METADATA
odoo14_addon_ssi_hr_cash_advance-14.0.1.15.0.dist-info/WHEEL
odoo14_addon_ssi_hr_cash_advance-14.0.1.15.0.dist-info/top_level.txt
odoo14_addon_ssi_hr_cash_advance-14.0.1.15.0.dist-info/RECORD
